home/__init__.py
home/admin.py
home/apps.py
home/models.py
home/tests.py
home/views.py
home/migrations/__init__.py
tum_common_x/__init__.py
tum_common_x/apps.py
tum_common_x/asgi.py
tum_common_x/settings.py
tum_common_x/signals.py
tum_common_x/urls.py
tum_common_x/wsgi.py
tumcommon_x-0.1.8.dist-info/licenses/LICENSE
tumcommon_x-0.1.8.dist-info/METADATA
tumcommon_x-0.1.8.dist-info/WHEEL
tumcommon_x-0.1.8.dist-info/top_level.txt
tumcommon_x-0.1.8.dist-info/RECORD
